[
  {
    "name": "MOODLEID1_",
    "value": "c%25E2%255B%257E%258E%250F%2588l%25CF",
    "domain": "bcpeducollege.elearningcommons.com",
    "path": "/",
    "expires": 1749468034.758439,
    "size": 47,
    "httpOnly": false,
    "secure": true,
    "session": false,
    "priority": "Medium",
    "sameParty": false,
    "sourceScheme": "Secure"
  },
  {
    "name": "MoodleSession",
    "value": "3uvdbp745c3rsrolba6p898run",
    "domain": "bcpeducollege.elearningcommons.com",
    "path": "/",
    "expires": -1,
    "size": 39,
    "httpOnly": false,
    "secure": true,
    "session": true,
    "sameSite": "None",
    "priority": "Medium",
    "sameParty": false,
    "sourceScheme": "Secure"
  },
  {
    "name": "_ga",
    "value": "GA1.1.573642522.1739446799",
    "domain": ".elearningcommons.com",
    "path": "/",
    "expires": 1778844035.733231,
    "size": 29,
    "httpOnly": false,
    "secure": false,
    "session": false,
    "priority": "Medium",
    "sameParty": false,
    "sourceScheme": "Secure"
  },
  {
    "name": "_ga_H5ZF5FJJ2B",
    "value": "GS1.1.1744284035.26.0.1744284035.60.0.0",
    "domain": ".elearningcommons.com",
    "path": "/",
    "expires": 1778844035.731401,
    "size": 53,
    "httpOnly": false,
    "secure": false,
    "session": false,
    "priority": "Medium",
    "sameParty": false,
    "sourceScheme": "Secure"
  },
  {
    "name": "MFA_TOKEN_28375",
    "value": "WyTfB%2FrI7R1D%2Fu%2FwQhT5Ssqx8rdfkClpeIm8wrLM8FIujRplJO9GJTyMxsNHbcnzXR9Ugnpdt5FAGVCbQqz31LJT5L%2FIIW5o%2F%2Fm9W0uVDYD3QhVk4PkHhvV9KVc5Us%2BV2YGjRfrpaOJqwrrwsiR0QmeMwmapjL%2Bl2B43mdW3%2FIIL6%2BA8mmVox57KyHzkhdE%2BKePGgop%2F7NW5Po8kJOqcyoCA8WZKCqAOioQOWVmf%2Bx0XShy0smCy5WUI%2FtTyO9rW9HZDVK02v6jVBRU7LMQKIvZGYIBpPkXIK7gaHwisZ41F4FG5rwwFNDGAce3S2oGGP%2FndHfWj36SsBnKturZhRg%3D%3D",
    "domain": "bcpeducollege.elearningcommons.com",
    "path": "/",
    "expires": 1745135599.518269,
    "size": 393,
    "httpOnly": true,
    "secure": false,
    "session": false,
    "priority": "Medium",
    "sameParty": false,
    "sourceScheme": "Secure"
  }
]